pymanifesto/__init__.py
pymanifesto/pymanifesto.py
pymanifesto-0.2.1.dist-info/AUTHORS.rst
pymanifesto-0.2.1.dist-info/LICENSE
pymanifesto-0.2.1.dist-info/METADATA
pymanifesto-0.2.1.dist-info/WHEEL
pymanifesto-0.2.1.dist-info/top_level.txt
pymanifesto-0.2.1.dist-info/RECORD
