Metadata-Version: 2.1
Name: pymanifesto
Version: 0.2.1
Summary: pymanifesto connects you to the Manifesto Project's database using Python.
Home-page: https://github.com/shimst3r/pymanifesto
Author: Nils P. Müller
Author-email: shimst3r@gmail.com
License: GNU General Public License v3
Keywords: pymanifesto
Platform: UNKNOWN
Classifier: Development Status :: 2 - Pre-Alpha
Classifier: Intended Audience :: Developers
Classifier: License :: OSI Approved :: GNU General Public License v3 (GPLv3)
Classifier: Natural Language :: English
Classifier: Programming Language :: Python :: 3
Classifier: Programming Language :: Python :: 3.7
Classifier: Programming Language :: Python :: 3.8
Requires-Python: >=3.7
